magedata_sdk/__init__.py
magedata_sdk/client.py
magedata_sdk/config.py
magedata_sdk/exceptions.py
magedata_sdk/models.py
magedata_sdk/processors.py
magedata_sdk-0.0.2.dist-info/LICENSE
magedata_sdk-0.0.2.dist-info/METADATA
magedata_sdk-0.0.2.dist-info/WHEEL
magedata_sdk-0.0.2.dist-info/top_level.txt
magedata_sdk-0.0.2.dist-info/RECORD
