Metadata-Version: 2.2
Name: magedata_sdk
Version: 0.0.2
Summary: Mage Data SDK for data anonymization
Home-page: https://github.com/mage-data/magedata_sdk
Author: Mage Data
Author-email: info@magedata.ai
License: Proprietary
Classifier: Intended Audience :: Developers
Classifier: License :: Other/Proprietary License
Classifier: Programming Language :: Python :: 3
Requires-Python: >=3.8
License-File: LICENSE
Requires-Dist: requests>=2.25.0
Requires-Dist: jsonpath-ng>=1.5.0
Requires-Dist: pydantic>=2.0.0
Requires-Dist: typing-extensions>=4.0.0
Dynamic: author
Dynamic: author-email
Dynamic: classifier
Dynamic: description
Dynamic: description-content-type
Dynamic: home-page
Dynamic: license
Dynamic: requires-dist
Dynamic: requires-python
Dynamic: summary
